tests/__init__.py
tests/test_example_data.py
tests/test_fitter.py
tests/test_pct_curve.py
vant_hoff_analysis/__init__.py
vant_hoff_analysis/fitter.py
vant_hoff_analysis/pct_curve.py
vant_hoff_analysis/result.py
vant_hoff_analysis-0.0.2.dist-info/METADATA
vant_hoff_analysis-0.0.2.dist-info/WHEEL
vant_hoff_analysis-0.0.2.dist-info/top_level.txt
vant_hoff_analysis-0.0.2.dist-info/RECORD
